[
  {
    "page_label": "Job Application Form",
    "fields": [
      {
        "field_id": "english_name",
        "label": "Name",
        "mandatory": "yes",
        "placeholder": "Enter name",
        "type": "text",
        "value": ""
      },
      {
        "field_id": "email",
        "label": "Email",
        "mandatory": "yes",
        "placeholder": "Enter email",
        "type": "text",
        "value": ""
      },
      {
        "field_id": "region",
        "label": "Select Region",
        "value": "---",
        "mandatory": "yes",
        "options": [
          {
            "label":"---"
          }
        ],
        "type": "select"
      },
      {
        "field_id": "district",
        "label": "Select district",
        "value": "Part-Time",
        "mandatory": "yes",
        "options": [
          {
            "label":"---"
          }
        ],
        "type": "select"
      },
      {
        "field_id": "driving_license",
        "label": "I confirm to have driving license.",
        "type": "checkbox",
        "value": "checked"
      },
      {
        "field_id": "Sex",
        "label": "select your sex.",
        "type": "radio",
        "value": "M",
        "radio_buttons": [
          {
            "label": "M"
          },
          {
            "label": "W"
          }
        ]
      },
      {
        "field_id": "complaint",
        "label": "",
        "type": "textarea",
        "placeholder": "type your complaint",
        "value": ""
      }
    ]
  }
]
